{"_id":"babel-plugin-filter-imports","_rev":"4-b75ad9a5244249b9ae11cb08b188d5b6","name":"babel-plugin-filter-imports","description":"A babel transform for filtering out imports","dist-tags":{"latest":"0.2.0"},"versions":{"0.1.0":{"name":"babel-plugin-filter-imports","version":"0.1.0","description":"A babel transform for filtering out imports","main":"index.js","scripts":{"test":"mocha"},"repository":{"type":"git","url":"https://github.com/ember-cli/babel-plugin-filter-imports"},"keywords":["babel","babel-plugin"],"author":{"name":"Martin Muñoz","email":"im.mmun@gmail.com"},"license":"MIT","bugs":{"url":"https://github.com/ember-cli/babel-plugin-filter-imports/issues"},"homepage":"https://github.com/ember-cli/babel-plugin-filter-imports","devDependencies":{"babel-core":"^5.5.3","mocha":"^2.2.5"},"gitHead":"6edc200c5b1c4e52368745c7232dc591ad40348f","_id":"babel-plugin-filter-imports@0.1.0","_shasum":"789b783948ebce1df7fd7750be7623d2346a83fe","_from":".","_npmVersion":"2.5.1","_nodeVersion":"0.12.0","_npmUser":{"name":"mmun","email":"im.mmun@gmail.com"},"maintainers":[{"name":"mmun","email":"im.mmun@gmail.com"}],"dist":{"shasum":"789b783948ebce1df7fd7750be7623d2346a83fe","tarball":"https://registry.npmjs.org/babel-plugin-filter-imports/-/babel-plugin-filter-imports-0.1.0.tgz"},"directories":{}},"0.2.0":{"name":"babel-plugin-filter-imports","version":"0.2.0","description":"A babel transform for filtering out imports","main":"index.js","scripts":{"test":"mocha"},"repository":{"type":"git","url":"git+https://github.com/ember-cli/babel-plugin-filter-imports.git"},"keywords":["babel","babel-plugin"],"author":{"name":"Martin Muñoz","email":"im.mmun@gmail.com"},"license":"MIT","bugs":{"url":"https://github.com/ember-cli/babel-plugin-filter-imports/issues"},"homepage":"https://github.com/ember-cli/babel-plugin-filter-imports","devDependencies":{"babel-core":"^5.5.3","mocha":"^2.2.5"},"gitHead":"d24c71cbf879b48ed5418f40fdf39a12460e674c","_id":"babel-plugin-filter-imports@0.2.0","_shasum":"b0840f6ae027ba80d8e1d01507534a220740187b","_from":".","_npmVersion":"2.11.2","_nodeVersion":"0.12.5","_npmUser":{"name":"mmun","email":"im.mmun@gmail.com"},"maintainers":[{"name":"mmun","email":"im.mmun@gmail.com"},{"name":"rwjblue","email":"me@rwjblue.com"},{"name":"stefanpenner","email":"stefan.penner@gmail.com"}],"dist":{"shasum":"b0840f6ae027ba80d8e1d01507534a220740187b","tarball":"https://registry.npmjs.org/babel-plugin-filter-imports/-/babel-plugin-filter-imports-0.2.0.tgz"},"directories":{}}},"readme":"ERROR: No README data found!","maintainers":[{"name":"mmun","email":"im.mmun@gmail.com"},{"name":"rwjblue","email":"me@rwjblue.com"},{"name":"stefanpenner","email":"stefan.penner@gmail.com"}],"time":{"modified":"2015-08-26T19:27:19.240Z","created":"2015-06-18T03:08:17.787Z","0.1.0":"2015-06-18T03:08:17.787Z","0.2.0":"2015-08-26T19:27:19.240Z"},"homepage":"https://github.com/ember-cli/babel-plugin-filter-imports","keywords":["babel","babel-plugin"],"repository":{"type":"git","url":"git+https://github.com/ember-cli/babel-plugin-filter-imports.git"},"author":{"name":"Martin Muñoz","email":"im.mmun@gmail.com"},"bugs":{"url":"https://github.com/ember-cli/babel-plugin-filter-imports/issues"},"license":"MIT","readmeFilename":"","_attachments":{},"_etag":"\"6S5SNB19I35QAUVKQTXKRWW2J\""}